jupyterlab_geojs/__init__.py
jupyterlab_geojs/gdalutils.py
jupyterlab_geojs/geojsfeature.py
jupyterlab_geojs/geojsfeaturelayer.py
jupyterlab_geojs/geojslayer.py
jupyterlab_geojs/geojsonfeature.py
jupyterlab_geojs/geojsosmlayer.py
jupyterlab_geojs/laspointcloud.py
jupyterlab_geojs/lasutils.py
jupyterlab_geojs/pointcloudfeature.py
jupyterlab_geojs/rasterfeature.py
jupyterlab_geojs/scene.py
jupyterlab_geojs/scenevalidator.py
jupyterlab_geojs/types.py
jupyterlab_geojs-0.3.3.dist-info/METADATA
jupyterlab_geojs-0.3.3.dist-info/RECORD
jupyterlab_geojs-0.3.3.dist-info/WHEEL
jupyterlab_geojs-0.3.3.dist-info/top_level.txt
