Metadata-Version: 2.1
Name: jupyterlab-geojs
Version: 0.3.3
Summary: A package for rendering GeoJS scenes in JupyterLab
Home-page: https://github.com/OpenGeoscience/jupyterlab_geojs
Author: john Tourtellott
Author-email: john.tourtellott@kitware.com
License: BSD
Keywords: jupyter,jupyterlab,extension,geojs
Platform: Linux
Platform: Mac OS X
Platform: Windows
Classifier: License :: OSI Approved :: BSD License
Classifier: Programming Language :: Python :: 3
